agent/__init__.py
agent/agent.py
collectors/__init__.py
collectors/cpu_stats/__init__.py
collectors/cpu_stats/cpu.py
collectors/cpu_stats/cpu_stats.py
collectors/disk_stats/__init__.py
collectors/disk_stats/disk_stats.py
collectors/inode_stats/__init__.py
collectors/inode_stats/inode.py
collectors/inode_stats/inode_stats.py
collectors/load_avg/__init__.py
collectors/load_avg/load_avg.py
collectors/open_files/__init__.py
collectors/open_files/open_files_linux.py
collectors/process_stats/__init__.py
collectors/process_stats/process_stats.py
collectors/utilities/__init__.py
collectors/utilities/hostname.py
collectors/utilities/process_output.py
collectors/utilities/string_helper.py
tests/__init__.py
tests/test_collector.py
tests/test_metrics.py
infra_agent-1.0.3.dist-info/METADATA
infra_agent-1.0.3.dist-info/WHEEL
infra_agent-1.0.3.dist-info/entry_points.txt
infra_agent-1.0.3.dist-info/top_level.txt
infra_agent-1.0.3.dist-info/RECORD
